pengtest/__init__.py
pengtest/autopullElmaPage.py
pengtest/canvas.py
pengtest/canvasUploadPage.py
pengtest/canvas_interface.py
pengtest/env_dialog.py
pengtest/env_wrapper.py
pengtest/extract_lms_archive.py
pengtest/grade_csv_uploader.py
pengtest/gui.py
pengtest/homePage.py
pengtest/moss.py
pengtest/moss_wrapper.py
pengtest/pengSplash.png
pengtest/resultsPage.py
pengtest/run_moss.py
pengtest/run_test_suite.py
pengtest/testSuiteCreator.py
pengtest/toolbox.py
pengtest/vmPage.py
pengtest/vm_wrapper.py
pengtest-0.9.9.6.1.dist-info/METADATA
pengtest-0.9.9.6.1.dist-info/WHEEL
pengtest-0.9.9.6.1.dist-info/entry_points.txt
pengtest-0.9.9.6.1.dist-info/top_level.txt
pengtest-0.9.9.6.1.dist-info/RECORD
