Metadata-Version: 2.1
Name: pengtest
Version: 0.9.9.6.1
Summary: Test suite tools for instructors
Home-page: https://github.com/tmaiello/herptest
Author: Emma Andrews, Gerard Avecilla, Matthew Baumaister, Tyler Maiello, Matt McDermott
Author-email: jjb@eng.ufl.edu
License: GPL 3
Platform: UNKNOWN
Requires-Dist: canvasapi
Requires-Dist: certifi
Requires-Dist: chardet
Requires-Dist: idna
Requires-Dist: mosspy
Requires-Dist: numpy
Requires-Dist: paramiko
Requires-Dist: pyside2
Requires-Dist: python-dotenv
Requires-Dist: requests
Requires-Dist: urllib3
Requires-Dist: virtualbox
Requires-Dist: vix
